{
    "r3.1st.basement": {
        "default": [
            "E5B7AA", "E5B7BB", "E5B7CC", "E5B7DD", "E5B7EE", "E5B7GG", "E5B7HH", "E5B7KK", "E5B7LL",
            "E5B7K1", "E5B7K2", "E5B7K3", "E5B7K4", "E5B7K5", "E5B7K6", "E5B7K7", "E5B7K8", "E5B7K9", "E5B7KB", "E5B7KC", "E5B7KD", "E5B7KE", "E5B7KF",  
            "E5B8AA",
            "E5B9DD", "E5B9EE", "E5B9EF", "E5B9AA", "E5B9BB", "E5B9CC", "E5B9CE", 
            "E5BAAA", "E5BACC", "E5BAAB", "E5BABB", "E5BABC", "E5BADD", "E5BAEE", "E5BAEF"
        ]
    },
    "r3.3rd.floor": {
        "default": [
            "E5B7AA", "E5B7BB", "E5B7CC", "E5B7GG", "E5B7KK", "E5B7LL",
            "E5B7K1", "E5B7K2", "E5B7K3", "E5B7K4", "E5B7K5", "E5B7K9", "E5B7KA", "E5B7KC", "E5B7KD", "E5B7KE", "E5B7KF",  
            "E5B9FF", "E5B9GG", "E5B9GH", "E5B9GI", "E5B9HH", "E5B9II", "E5B9IJ",
            "E5BAAA", "E5BACC", "E5BAAB"
        ]
    },
    "r4.rainbow": {
        "lunch": [ "REST000003" ]
    },
    "r4.oasis": {
        "lunch": [ "REST000005" ]
    },
    "r4.milkyway": {
        "lunch": [ "REST000004" ]
    },
    "r5.1st.basement": {
        "default": [ "REST000007" ]
    },
    "r5.2nd.basement": {
        "default": [ "REST000008" ]
    },
    "r5.5th.floor": {
        "default": [ "REST000006" ]
    },
    "smart.1st.floor": {
        "breakfast": [
            "E13CAA", "E13CBB", "E13CEE", "E13CGG", "E13CHH", "E13CII", "E13CJJ", "E13CWW", "E13CXX", "E13CZZ"
        ],
        "lunch": [
            "E13CAA", "E13CBB", "E13CD1", "E13CDD", "E13CMM", "E13CGG", "E13CHH", "E13CWW", "E13CYY", "E13CZ1"
        ],
        "dinner": [
            "E13CAA", "E13CCC", "E13CEE", "E13CFF", "E13CGG", "E13CHH", "E13CPP", "E13CWW", "E13CYY"
        ]
    }
}
